pyroll/integral_thermal/__init__.py
pyroll/integral_thermal/cooling_pipe.py
pyroll/integral_thermal/helper.py
pyroll/integral_thermal/report.py
pyroll/integral_thermal/roll_pass.py
pyroll/integral_thermal/transport.py
pyroll_integral_thermal-3.0.0.dist-info/METADATA
pyroll_integral_thermal-3.0.0.dist-info/WHEEL
pyroll_integral_thermal-3.0.0.dist-info/licenses/LICENSE
pyroll_integral_thermal-3.0.0.dist-info/RECORD
